bulletchess-0.4.0.dist-info/RECORD
bulletchess-0.4.0.dist-info/WHEEL
bulletchess-0.4.0.dist-info/top_level.txt
bulletchess-0.4.0.dist-info/METADATA
bulletchess-0.4.0.dist-info/licenses/LICENSE
bulletchess/_core.cpython-313-darwin.so
bulletchess/__init__.pyi
bulletchess/__init__.py
bulletchess/py.typed
bulletchess/pgn/__init__.pyi
bulletchess/utils/__init__.pyi
