Metadata-Version: 2.4
Name: bulletchess
Version: 0.4.0
Summary: A high performance C Extension for chess
Author-email: Jordan Zedeck <mail@jordanzedeck.com>
License-Expression: GPL-3.0-or-later
Project-URL: Homepage, https://zedeckj.github.io/bulletchess/index.html
Project-URL: Issues, https://github.com/zedeckj/bulletchess/issues
Requires-Python: >=3.13
License-File: LICENSE
Dynamic: license-file
